COPYING.txt
MANIFEST.in
NEWS.rst
README.rst
setup.py
bond/__init__.py
bond/protocols.py
bond/JavaScript/__init__.py
bond/PHP/__init__.py
bond/Perl/__init__.py
bond/Python/__init__.py
bond/drivers/COPYING.txt
bond/drivers/README.rst
bond/drivers/JavaScript/bond.json
bond/drivers/JavaScript/stage1.js
bond/drivers/JavaScript/stage2.js
bond/drivers/PHP/bond.json
bond/drivers/PHP/stage1.php
bond/drivers/PHP/stage2.php
bond/drivers/Perl/bond.json
bond/drivers/Perl/stage1.pl
bond/drivers/Perl/stage2.pl
bond/drivers/Python/bond.json
bond/drivers/Python/stage1.py
bond/drivers/Python/stage2.py
python_bond.egg-info/PKG-INFO
python_bond.egg-info/SOURCES.txt
python_bond.egg-info/dependency_links.txt
python_bond.egg-info/requires.txt
python_bond.egg-info/top_level.txt
tests/__init__.py
tests/test_JavaScript.py
tests/test_PHP.py
tests/test_PHP_Perl.py
tests/test_Perl.py
tests/test_Python.py
tests/test_api_v0.py
tests/test_bond.py