Metadata-Version: 1.1
Name: python-bond
Version: 1.0
Summary: transparent remote/recursive evaluation between Python and other languages
Home-page: https://github.com/wavexx/python-bond
Author: Yuri D'Elia
Author-email: wavexx@thregr.org
License: GPL2
Keywords: javascript php perl python
Platform: UNKNOWN
Classifier: Development Status :: 5 - Production/Stable
Classifier: Environment :: Console
Classifier: Environment :: No Input/Output (Daemon)
Classifier: Intended Audience :: Developers
Classifier: License :: OSI Approved :: GNU General Public License v2 (GPLv2)
Classifier: Operating System :: POSIX
Classifier: Operating System :: Unix
Classifier: Programming Language :: JavaScript
Classifier: Programming Language :: PHP
Classifier: Programming Language :: Perl
Classifier: Programming Language :: Python :: 2.7
Classifier: Programming Language :: Python :: 3
Classifier: Programming Language :: Python
Classifier: Topic :: Software Development :: Interpreters
Classifier: Topic :: Software Development :: Libraries :: Python Modules
Classifier: Topic :: Software Development
